puccinialin/__init__.py
puccinialin/__main__.py
puccinialin/_setup_rust.py
puccinialin/_target.py
puccinialin/py.typed
puccinialin-0.1.4.dist-info/METADATA
puccinialin-0.1.4.dist-info/WHEEL
puccinialin-0.1.4.dist-info/entry_points.txt
puccinialin-0.1.4.dist-info/RECORD
