Metadata-Version: 2.4
Name: puccinialin
Version: 0.1.4
Summary: Install rust into a temporary directory for boostrapping a rust-based build backend
Project-URL: repository, https://github.com/konstin/puccinialin
Author-email: konstin <konstin@mailbox.org>
Requires-Python: >=3.9
Requires-Dist: httpx<0.29,>=0.28.1
Requires-Dist: platformdirs<5,>=4.3.6
Requires-Dist: tqdm<5,>=4.67.1
